{
  "transactions": [
    {
      "id": 1,
      "description": "Desenvolvimento de site",
      "type": "income",
      "category": "Venda",
      "price": 14000,
      "createdAt": "2022-11-07T21:44:57.705Z"
    },
    {
      "id": 2,
      "description": "Alugel",
      "type": "outcome",
      "category": "Casa",
      "price": 2000,
      "createdAt": "2022-11-07T21:50:57.705Z"
    },
    {
      "id": 3,
      "description": "Ignite Rocketseat",
      "type": "outcome",
      "category": "Educação",
      "price": 1780,
      "createdAt": "2022-11-07T21:10:57.705Z"
    },
    {
      "description": "Almoço",
      "category": "Alimentação",
      "price": 120,
      "type": "outcome",
      "createdAt": "2022-11-09T21:46:58.898Z",
      "id": 4
    },
    {
      "description": "Sorvete",
      "category": "Alimentação",
      "price": 12,
      "type": "outcome",
      "createdAt": "2022-11-09T22:00:29.895Z",
      "id": 5
    }
  ]
}